holland/__init__.py
holland/evolution/__init__.py
holland/evolution/breeding.py
holland/evolution/crossover.py
holland/evolution/evaluation.py
holland/evolution/evolution.py
holland/evolution/mutation.py
holland/evolution/selection.py
holland/library/__init__.py
holland/library/crossover_functions.py
holland/library/fitness_weighting_functions.py
holland/library/mutation_functions.py
holland/storage/__init__.py
holland/storage/fitness.py
holland/storage/genomes_and_fitnesses.py
holland/storage/storage_manager.py
holland/storage/utils.py
holland/utils/__init__.py
holland/utils/utils.py
tests/__init__.py
tests/evolution/__init__.py
tests/evolution/test_breeding.py
tests/evolution/test_crossover.py
tests/evolution/test_evaluation.py
tests/evolution/test_evolution.py
tests/evolution/test_mutation.py
tests/evolution/test_selection.py
tests/library/__init__.py
tests/library/test_crossover_functions.py
tests/library/test_fitness_weighting_functions.py
tests/library/test_mutation_functions.py
tests/storage/__init__.py
tests/storage/test_fitness.py
tests/storage/test_genomes_and_fitnesses.py
tests/storage/test_storage_manager.py
tests/storage/test_utils.py
tests/utils/__init__.py
tests/utils/test_utils.py
holland-0.0.2.dist-info/LICENSE
holland-0.0.2.dist-info/METADATA
holland-0.0.2.dist-info/WHEEL
holland-0.0.2.dist-info/top_level.txt
holland-0.0.2.dist-info/RECORD
