Metadata-Version: 2.1
Name: holland
Version: 0.0.2
Summary: Genetic Algorithm Library
Home-page: https://github.com/lambdalife/holland
Author: Lambda Life
Author-email: lambdalife@henrywoody.com
License: UNKNOWN
Platform: UNKNOWN
Classifier: Programming Language :: Python :: 3
Classifier: License :: OSI Approved :: MIT License
Classifier: Operating System :: OS Independent
